tracealllines/LICENSE
tracealllines/README.MD
tracealllines/__init__.py
tracealllines/requirements.txt
tracealllines/thirdparty.json
tracealllines-0.10.dist-info/LICENSE.rst
tracealllines-0.10.dist-info/METADATA
tracealllines-0.10.dist-info/WHEEL
tracealllines-0.10.dist-info/top_level.txt
tracealllines-0.10.dist-info/RECORD
